droit/__init__.py
droit/analyzer.py
droit/dumper.py
droit/legacy.py
droit/loader.py
droit/models.py
droit/plugins/input/inp/info.json
droit/plugins/input/inp/main.py
droit/plugins/input/rank/info.json
droit/plugins/input/rank/main.py
droit/plugins/input/session/info.json
droit/plugins/input/session/main.py
droit/plugins/input/simt/info.json
droit/plugins/input/simt/main.py
droit/plugins/input/srtx/info.json
droit/plugins/input/srtx/main.py
droit/plugins/input/text/info.json
droit/plugins/input/text/main.py
droit/plugins/input/text/req.py
droit/plugins/output/eval.rand/main.py
droit/plugins/output/eval.session/main.py
droit/plugins/output/get/main.py
droit/plugins/output/text/main.py
droit/plugins/output/var/main.py
droit-1.1.2.dist-info/LICENSE
droit-1.1.2.dist-info/METADATA
droit-1.1.2.dist-info/WHEEL
droit-1.1.2.dist-info/top_level.txt
droit-1.1.2.dist-info/RECORD
