Metadata-Version: 2.1
Name: droit
Version: 1.1.2
Summary: Simple library for creating bots
Home-page: https://github.com/jarinox/python-droit
Author: Jakob Stolze
Author-email: jarinox@wolke7.de
License: LGPLv2.1
Platform: UNKNOWN
Requires-Python: >=3.6
License-File: LICENSE
Requires-Dist: parse
